autreach/__init__.py
autreach/api/__init__.py
autreach/api/main.py
autreach/api/common/__init__.py
autreach/api/common/config.py
autreach/api/common/constants.py
autreach/api/common/logger.py
autreach/api/common/utils/__init__.py
autreach/api/common/utils/exception_handlers.py
autreach/api/common/utils/exceptions.py
autreach/api/common/utils/response.py
autreach/api/common/utils/static_files.py
autreach/cli/__init__.py
autreach/cli/main.py
autreach/cli/server/__init__.py
autreach/cli/server/health.py
autreach/cli/server/launcher.py
autreach/cli/server/port.py
autreach/cli/server/uvicorn_server.py
autreach/ui/__init__.py
autreach/ui/index.html
autreach/ui/vite.svg
autreach/ui/assets/index-BC1T9eNl.js
autreach/ui/assets/index-DctOUoAE.css
autreach-0.0.1.dist-info/METADATA
autreach-0.0.1.dist-info/WHEEL
autreach-0.0.1.dist-info/entry_points.txt
autreach-0.0.1.dist-info/licenses/LICENSE
autreach-0.0.1.dist-info/RECORD
