Metadata-Version: 2.4
Name: autreach
Version: 0.0.1
Summary: Automate LinkedIn job discovery and personalized outreach with a real-time control dashboard.
Author: Aryan Khurana
License: MIT
License-File: LICENSE
Requires-Python: >=3.12
Requires-Dist: colorama>=0.4.6
Requires-Dist: fastapi[standard]>=0.115.12
Requires-Dist: pydantic-settings>=2.9.1
Requires-Dist: selenium>=4.32.0
Requires-Dist: sqlmodel>=0.0.14
Requires-Dist: typer>=0.9.0
Requires-Dist: uvicorn>=0.27.0
